hnap/__init__.py
hnap/__main__.py
hnap/cli.py
hnap/const.py
hnap/devices.py
hnap/helpers.py
hnap/soapclient.py
hnap-1.0.1.dist-info/LICENSE
hnap-1.0.1.dist-info/METADATA
hnap-1.0.1.dist-info/WHEEL
hnap-1.0.1.dist-info/entry_points.txt
hnap-1.0.1.dist-info/top_level.txt
hnap-1.0.1.dist-info/RECORD
