Metadata-Version: 2.1
Name: hnap
Version: 1.0.1
Summary: Python clients for HNAP devices
Author-email: Luis Lopez <luis@cuarentaydos.com>
Project-URL: Homepage, https://github.com/ldotlopez/python-hnap
Project-URL: Bug Tracker, https://github.com/ldotlopez/python-hnap/issues
Classifier: Programming Language :: Python :: 3
Classifier: License :: OSI Approved :: MIT License
Classifier: Operating System :: OS Independent
Requires-Python: >=3.11
License-File: LICENSE
Requires-Dist: requests >=2.27.1
Requires-Dist: xmltodict >=0.12.0
Requires-Dist: importlib-metadata ; python_version >= "3.11"
